Workbook

Sheet Summary
A1: Adikt — 2027 Inventory
A2: Snapshot from Shopify on 9 Oct 2026 plus a 2027 reorder plan. Inputs live on 'Assumptions' (yellow cells).
A4: Metric | B4: Value
A5: Units on hand (all products) | B5: ='Current Stock'!G99 -> 686
A6: Retail value on hand | B6: ='Current Stock'!H99 -> 20275.99
A7: Units on hand — Active products | B7: ='Current Stock'!G100 -> 450
A8: Units on hand — Archived / Draft (dead stock to clear) | B8: ='Current Stock'!G101 -> 236
A9: Retail value — Archived / Draft | B9: ='Current Stock'!H101 -> 12100.99
A10: Units sold, trailing 12 months (all) | B10: =SUM('Monthly History'!B16:B27) -> 118
A11: 2027 demand forecast — Active SKUs | B11: ='2027 Plan'!I27 -> 136
A12: Reorder units needed for 2027 | B12: ='2027 Plan'!K27 -> 28
A13: Reorder value at retail | B13: ='2027 Plan'!L27 -> 2905
A14: Active variants out of stock | B14: =COUNTIF('2027 Plan'!N5:N26,"OUT*") -> 4
A15: Demand growth assumption | B15: =Assumptions!$B$5 -> 0.2

Sheet Assumptions
A1: 2027 Inventory Plan — Assumptions
A2: Adikt (adikt.site). Shopify data pulled 2026-10-09. Yellow cells are inputs: change them and every sheet recalculates.
A4: Assumption | B4: Value | C4: Note
A5: Demand growth for 2027 vs. trailing 12 months | B5: 0.2 | C5: Placeholder. Set to your own expectation (e.g. new drops, ad spend).
A6: Safety stock (months of demand held as buffer) | B6: 2 | C6: Covers supplier delays and a viral spike. 2 months is a common starting point for small apparel brands.
A7: Supplier lead time (months) | B7: 1 | C7: Placeholder: time from placing a reorder to stock on shelf. Printed in Houston per product descriptions; adjust to your vendor.
A8: Max months of sales history used | B8: 12 | C8: Trailing window for the sales rate. Newer products use months since launch instead (min 1).
A9: Plan date (today) | B9: 46304 | C9: Date the Shopify data was pulled.
A11: Data notes
A12: • Sales = Shopify Analytics net items sold, 9 Oct 2025 – 9 Oct 2026, per product/variant.
A13: • 47 units ($2,650 net) in that window have no product title in Shopify Analytics (deleted products or custom line items). They are excluded from per-SKU forecasts but included in the Monthly History totals.
A14: • Stock = Shopify inventoryQuantity summed across locations, 9 Oct 2026. Negative/zero stock shows as '-'.
A15: • Archived products are listed on 'Current Stock' (they still hold units) but are not planned for 2027 unless you set them back to Active.
A16: • Seasonality on 'Monthly 2027' is the share of the last 24 months' units sold in each calendar month.

Sheet Current Stock
A1: Current Stock by Variant — 9 Oct 2026
A3: Product | B3: Variant | C3: SKU | D3: Status | E3: Type | F3: Price ($) | G3: On hand (units) | H3: Retail value ($)
A4: "JOJO" Vintage Black Hoodie | B4: S | D4: Active | E4: Hoodie | F4: 80 | G4: 3 | H4: =F4*G4 -> 240
A5: "JOJO" Vintage Black Hoodie | B5: M | D5: Active | E5: Hoodie | F5: 80 | G5: 4 | H5: =F5*G5 -> 320
A6: "JOJO" Vintage Black Hoodie | B6: L | D6: Active | E6: Hoodie | F6: 80 | G6: 3 | H6: =F6*G6 -> 240
A7: "JOJO" Vintage Black Hoodie | B7: XL | D7: Active | E7: Hoodie | F7: 80 | G7: 2 | H7: =F7*G7 -> 160
A8: ADIKT Blue Washed Zip Up | B8: S | D8: Active | E8: Hoodie | F8: 80 | G8: 2 | H8: =F8*G8 -> 160
A9: ADIKT Blue Washed Zip Up | B9: M | D9: Active | E9: Hoodie | F9: 80 | G9: 2 | H9: =F9*G9 -> 160
A10: ADIKT Blue Washed Zip Up | B10: L | D10: Active | E10: Hoodie | F10: 80 | G10: 3 | H10: =F10*G10 -> 240
A11: ADIKT Blue Washed Zip Up | B11: XL | D11: Active | E11: Hoodie | F11: 80 | G11: 2 | H11: =F11*G11 -> 160
A12: ADIKT Crew Socks – Pink | B12: Pink | C12: PINK-CS | D12: Active | E12: Socks | F12: 10 | G12: 94 | H12: =F12*G12 -> 940
A13: ADIKT Crew Socks – Red | B13: Red | C13: RED-CS | D13: Active | E13: Socks | F13: 10 | G13: 91 | H13: =F13*G13 -> 910
A14: ADIKT Crew Socks – White | B14: White | C14: WHT-CS | D14: Active | E14: Socks | F14: 10 | G14: 91 | H14: =F14*G14 -> 910
A15: ADIKT Crew Socks – Yellow | B15: Yellow | C15: SFT-YLL-CS | D15: Active | E15: Socks | F15: 10 | G15: 90 | H15: =F15*G15 -> 900
A16: ADIKT Navy Mesh Retro Gym Shorts | B16: S | D16: Active | E16: Shorts | F16: 45 | G16: 8 | H16: =F16*G16 -> 360
A17: ADIKT Navy Mesh Retro Gym Shorts | B17: M | D17: Active | E17: Shorts | F17: 45 | G17: 15 | H17: =F17*G17 -> 675
A18: ADIKT Navy Mesh Retro Gym Shorts | B18: L | D18: Active | E18: Shorts | F18: 45 | G18: 11 | H18: =F18*G18 -> 495
A19: ADIKT Navy Mesh Retro Gym Shorts | B19: XL | D19: Active | E19: Shorts | F19: 45 | G19: 21 | H19: =F19*G19 -> 945
A20: ADIKT Navy Mesh Retro Gym Shorts | B20: XXL | D20: Active | E20: Shorts | F20: 45 | G20: 8 | H20: =F20*G20 -> 360
A21: ADIKT Red Racing Zip Up | B21: S | D21: Active | E21: Hoodie | F21: 120 | G21: 0 | H21: =F21*G21 -> 0
A22: ADIKT Red Racing Zip Up | B22: M | D22: Active | E22: Hoodie | F22: 120 | G22: 0 | H22: =F22*G22 -> 0
A23: ADIKT Red Racing Zip Up | B23: L | D23: Active | E23: Hoodie | F23: 120 | G23: 0 | H23: =F23*G23 -> 0
A24: ADIKT Red Racing Zip Up | B24: XL | D24: Active | E24: Hoodie | F24: 120 | G24: 0 | H24: =F24*G24 -> 0
A25: ADIKT Red Racing Zip Up | B25: XXL | D25: Active | E25: Hoodie | F25: 120 | G25: 0 | H25: =F25*G25 -> 0
A26: DESERT CAMO TEE | B26: S | D26: Draft | F26: 45 | G26: 1 | H26: =F26*G26 -> 45
A27: DESERT CAMO TEE | B27: XL | D27: Draft | F27: 45 | G27: 1 | H27: =F27*G27 -> 45
A28: "AADIKT©" WHITE | B28: S | D28: Archived | F28: 30 | G28: 4 | H28: =F28*G28 -> 120
A29: "AADIKT©" WHITE | B29: M | D29: Archived | F29: 30 | G29: 4 | H29: =F29*G29 -> 120
A30: "AADIKT©" WHITE | B30: L | D30: Archived | F30: 30 | G30: 8 | H30: =F30*G30 -> 240
A31: "AADIKT©" WHITE | B31: XL | D31: Archived | F31: 30 | G31: 4 | H31: =F31*G31 -> 120
A32: "AADIKT©" WHITE | B32: XXL | D32: Archived | F32: 30 | G32: 3 | H32: =F32*G32 -> 90
A33: "FOR YOU" BOXY TEE | B33: L | D33: Archived | F33: 35 | G33: 4 | H33: =F33*G33 -> 140
A34: "FOR YOU" BOXY TEE | B34: XL | D34: Archived | F34: 35 | G34: 3 | H34: =F34*G34 -> 105
A35: "FOR YOU" BOXY TEE | B35: XXL | D35: Archived | F35: 35 | G35: 2 | H35: =F35*G35 -> 70
A36: "FOR YOU" BOXY TEE | B36: S | D36: Archived | F36: 35 | G36: 3 | H36: =F36*G36 -> 105
A37: "FOR YOU" BOXY TEE | B37: L | D37: Archived | F37: 35 | G37: 5 | H37: =F37*G37 -> 175
... A98: ‘METALLIC’ T-SHIRT | B98: XL | D98: Archived | F98: 45 | G98: 1 | H98: =F98*G98 -> 45
A99: Total | G99: =SUM(G4:G98) -> 686 | H99: =SUM(H4:H98) -> 20275.99
A100: Of which Active | G100: =SUMIFS(G4:G98,D4:D98,"Active") -> 450 | H100: =SUMIFS(H4:H98,D4:D98,"Active") -> 8175
A101: Of which Archived / Draft | G101: =G99-G100 -> 236 | H101: =H99-H100 -> 12100.99

Sheet 2027 Plan
A1: 2027 Reorder Plan — Active Products
A2: Reorder qty = 2027 demand + safety stock − on hand. Lead-time demand flags variants that run out before a reorder can land.
A4: Product | B4: Variant | C4: Price ($) | D4: On hand (units) | E4: Launched | F4: Months of history | G4: Units sold (trailing 12 mo) | H4: Monthly sales rate | I4: 2027 demand (units) | J4: Safety stock (units) | K4: Reorder qty for 2027 | L4: Reorder cost at retail ($) | M4: Months of cover now | N4: Status
A5: "JOJO" Vintage Black Hoodie | B5: S | C5: ='Current Stock'!F4 -> 80 | D5: ='Current Stock'!G4 -> 3 | E5: 46107 | F5: =MIN(Assumptions!$B$8,MAX(1,ROUND((Assumptions!$B$9-E5)/30.4,1))) -> 6.5 | G5: 0 | H5: =G5/F5 -> 0 | I5: =ROUNDUP(H5*12*(1+Assumptions!$B$5),0) -> 0 | J5: =ROUNDUP(H5*Assumptions!$B$6,0) -> 0 | K5: =MAX(0,I5+J5-D5) -> 0 | L5: =K5*C5 -> 0 | M5: =IF(H5=0,"No sales",D5/(H5*(1+Assumptions!$B$5))) -> No sales | N5: =IF(AND(D5=0,H5>0),"OUT OF STOCK — reorder now",IF(H5=0,"No sales yet — hold",IF(D5<H5*(1+Assumptions!$B$5)*(Assumptions!$B$7+Assumptions!$B$6),"Reorder soon",IF(K5=0,"Covered for 2027","Reorder in 2027")))) -> No sales yet — hold
A6: "JOJO" Vintage Black Hoodie | B6: M | C6: ='Current Stock'!F5 -> 80 | D6: ='Current Stock'!G5 -> 4 | E6: 46107 | F6: =MIN(Assumptions!$B$8,MAX(1,ROUND((Assumptions!$B$9-E6)/30.4,1))) -> 6.5 | G6: 0 | H6: =G6/F6 -> 0 | I6: =ROUNDUP(H6*12*(1+Assumptions!$B$5),0) -> 0 | J6: =ROUNDUP(H6*Assumptions!$B$6,0) -> 0 | K6: =MAX(0,I6+J6-D6) -> 0 | L6: =K6*C6 -> 0 | M6: =IF(H6=0,"No sales",D6/(H6*(1+Assumptions!$B$5))) -> No sales | N6: =IF(AND(D6=0,H6>0),"OUT OF STOCK — reorder now",IF(H6=0,"No sales yet — hold",IF(D6<H6*(1+Assumptions!$B$5)*(Assumptions!$B$7+Assumptions!$B$6),"Reorder soon",IF(K6=0,"Covered for 2027","Reorder in 2027")))) -> No sales yet — hold
A7: "JOJO" Vintage Black Hoodie | B7: L | C7: ='Current Stock'!F6 -> 80 | D7: ='Current Stock'!G6 -> 3 | E7: 46107 | F7: =MIN(Assumptions!$B$8,MAX(1,ROUND((Assumptions!$B$9-E7)/30.4,1))) -> 6.5 | G7: 0 | H7: =G7/F7 -> 0 | I7: =ROUNDUP(H7*12*(1+Assumptions!$B$5),0) -> 0 | J7: =ROUNDUP(H7*Assumptions!$B$6,0) -> 0 | K7: =MAX(0,I7+J7-D7) -> 0 | L7: =K7*C7 -> 0 | M7: =IF(H7=0,"No sales",D7/(H7*(1+Assumptions!$B$5))) -> No sales | N7: =IF(AND(D7=0,H7>0),"OUT OF STOCK — reorder now",IF(H7=0,"No sales yet — hold",IF(D7<H7*(1+Assumptions!$B$5)*(Assumptions!$B$7+Assumptions!$B$6),"Reorder soon",IF(K7=0,"Covered for 2027","Reorder in 2027")))) -> No sales yet — hold
A8: "JOJO" Vintage Black Hoodie | B8: XL | C8: ='Current Stock'!F7 -> 80 | D8: ='Current Stock'!G7 -> 2 | E8: 46107 | F8: =MIN(Assumptions!$B$8,MAX(1,ROUND((Assumptions!$B$9-E8)/30.4,1))) -> 6.5 | G8: 1 | H8: =G8/F8 -> 0.15384615 | I8: =ROUNDUP(H8*12*(1+Assumptions!$B$5),0) -> 3 | J8: =ROUNDUP(H8*Assumptions!$B$6,0) -> 1 | K8: =MAX(0,I8+J8-D8) -> 2 | L8: =K8*C8 -> 160 | M8: =IF(H8=0,"No sales",D8/(H8*(1+Assumptions!$B$5))) -> 10.833333 | N8: =IF(AND(D8=0,H8>0),"OUT OF STOCK — reorder now",IF(H8=0,"No sales yet — hold",IF(D8<H8*(1+Assumptions!$B$5)*(Assumptions!$B$7+Assumptions!$B$6),"Reorder soon",IF(K8=0,"Covered for 2027","Reorder in 2027")))) -> Reorder in 2027
A9: ADIKT Blue Washed Zip Up | B9: S | C9: ='Current Stock'!F8 -> 80 | D9: ='Current Stock'!G8 -> 2 | E9: 46272 | F9: =MIN(Assumptions!$B$8,MAX(1,ROUND((Assumptions!$B$9-E9)/30.4,1))) -> 1.1 | G9: 0 | H9: =G9/F9 -> 0 | I9: =ROUNDUP(H9*12*(1+Assumptions!$B$5),0) -> 0 | J9: =ROUNDUP(H9*Assumptions!$B$6,0) -> 0 | K9: =MAX(0,I9+J9-D9) -> 0 | L9: =K9*C9 -> 0 | M9: =IF(H9=0,"No sales",D9/(H9*(1+Assumptions!$B$5))) -> No sales | N9: =IF(AND(D9=0,H9>0),"OUT OF STOCK — reorder now",IF(H9=0,"No sales yet — hold",IF(D9<H9*(1+Assumptions!$B$5)*(Assumptions!$B$7+Assumptions!$B$6),"Reorder soon",IF(K9=0,"Covered for 2027","Reorder in 2027")))) -> No sales yet — hold
A10: ADIKT Blue Washed Zip Up | B10: M | C10: ='Current Stock'!F9 -> 80 | D10: ='Current Stock'!G9 -> 2 | E10: 46272 | F10: =MIN(Assumptions!$B$8,MAX(1,ROUND((Assumptions!$B$9-E10)/30.4,1))) -> 1.1 | G10: 0 | H10: =G10/F10 -> 0 | I10: =ROUNDUP(H10*12*(1+Assumptions!$B$5),0) -> 0 | J10: =ROUNDUP(H10*Assumptions!$B$6,0) -> 0 | K10: =MAX(0,I10+J10-D10) -> 0 | L10: =K10*C10 -> 0 | M10: =IF(H10=0,"No sales",D10/(H10*(1+Assumptions!$B$5))) -> No sales | N10: =IF(AND(D10=0,H10>0),"OUT OF STOCK — reorder now",IF(H10=0,"No sales yet — hold",IF(D10<H10*(1+Assumptions!$B$5)*(Assumptions!$B$7+Assumptions!$B$6),"Reorder soon",IF(K10=0,"Covered for 2027","Reorder in 2027")))) -> No sales yet — hold
A11: ADIKT Blue Washed Zip Up | B11: L | C11: ='Current Stock'!F10 -> 80 | D11: ='Current Stock'!G10 -> 3 | E11: 46272 | F11: =MIN(Assumptions!$B$8,MAX(1,ROUND((Assumptions!$B$9-E11)/30.4,1))) -> 1.1 | G11: 0 | H11: =G11/F11 -> 0 | I11: =ROUNDUP(H11*12*(1+Assumptions!$B$5),0) -> 0 | J11: =ROUNDUP(H11*Assumptions!$B$6,0) -> 0 | K11: =MAX(0,I11+J11-D11) -> 0 | L11: =K11*C11 -> 0 | M11: =IF(H11=0,"No sales",D11/(H11*(1+Assumptions!$B$5))) -> No sales | N11: =IF(AND(D11=0,H11>0),"OUT OF STOCK — reorder now",IF(H11=0,"No sales yet — hold",IF(D11<H11*(1+Assumptions!$B$5)*(Assumptions!$B$7+Assumptions!$B$6),"Reorder soon",IF(K11=0,"Covered for 2027","Reorder in 2027")))) -> No sales yet — hold
A12: ADIKT Blue Washed Zip Up | B12: XL | C12: ='Current Stock'!F11 -> 80 | D12: ='Current Stock'!G11 -> 2 | E12: 46272 | F12: =MIN(Assumptions!$B$8,MAX(1,ROUND((Assumptions!$B$9-E12)/30.4,1))) -> 1.1 | G12: 0 | H12: =G12/F12 -> 0 | I12: =ROUNDUP(H12*12*(1+Assumptions!$B$5),0) -> 0 | J12: =ROUNDUP(H12*Assumptions!$B$6,0) -> 0 | K12: =MAX(0,I12+J12-D12) -> 0 | L12: =K12*C12 -> 0 | M12: =IF(H12=0,"No sales",D12/(H12*(1+Assumptions!$B$5))) -> No sales | N12: =IF(AND(D12=0,H12>0),"OUT OF STOCK — reorder now",IF(H12=0,"No sales yet — hold",IF(D12<H12*(1+Assumptions!$B$5)*(Assumptions!$B$7+Assumptions!$B$6),"Reorder soon",IF(K12=0,"Covered for 2027","Reorder in 2027")))) -> No sales yet — hold
A13: ADIKT Crew Socks – Pink | B13: Pink | C13: ='Current Stock'!F12 -> 10 | D13: ='Current Stock'!G12 -> 94 | E13: 46167 | F13: =MIN(Assumptions!$B$8,MAX(1,ROUND((Assumptions!$B$9-E13)/30.4,1))) -> 4.5 | G13: 6 | H13: =G13/F13 -> 1.3333333 | I13: =ROUNDUP(H13*12*(1+Assumptions!$B$5),0) -> 20 | J13: =ROUNDUP(H13*Assumptions!$B$6,0) -> 3 | K13: =MAX(0,I13+J13-D13) -> 0 | L13: =K13*C13 -> 0 | M13: =IF(H13=0,"No sales",D13/(H13*(1+Assumptions!$B$5))) -> 58.75 | N13: =IF(AND(D13=0,H13>0),"OUT OF STOCK — reorder now",IF(H13=0,"No sales yet — hold",IF(D13<H13*(1+Assumptions!$B$5)*(Assumptions!$B$7+Assumptions!$B$6),"Reorder soon",IF(K13=0,"Covered for 2027","Reorder in 2027")))) -> Covered for 2027
A14: ADIKT Crew Socks – Red | B14: Red | C14: ='Current Stock'!F13 -> 10 | D14: ='Current Stock'!G13 -> 91 | E14: 46164 | F14: =MIN(Assumptions!$B$8,MAX(1,ROUND((Assumptions!$B$9-E14)/30.4,1))) -> 4.6 | G14: 8 | H14: =G14/F14 -> 1.7391304 | I14: =ROUNDUP(H14*12*(1+Assumptions!$B$5),0) -> 26 | J14: =ROUNDUP(H14*Assumptions!$B$6,0) -> 4 | K14: =MAX(0,I14+J14-D14) -> 0 | L14: =K14*C14 -> 0 | M14: =IF(H14=0,"No sales",D14/(H14*(1+Assumptions!$B$5))) -> 43.604167 | N14: =IF(AND(D14=0,H14>0),"OUT OF STOCK — reorder now",IF(H14=0,"No sales yet — hold",IF(D14<H14*(1+Assumptions!$B$5)*(Assumptions!$B$7+Assumptions!$B$6),"Reorder soon",IF(K14=0,"Covered for 2027","Reorder in 2027")))) -> Covered for 2027
A15: ADIKT Crew Socks – White | B15: White | C15: ='Current Stock'!F14 -> 10 | D15: ='Current Stock'!G14 -> 91 | E15: 46169 | F15: =MIN(Assumptions!$B$8,MAX(1,ROUND((Assumptions!$B$9-E15)/30.4,1))) -> 4.4 | G15: 8 | H15: =G15/F15 -> 1.8181818 | I15: =ROUNDUP(H15*12*(1+Assumptions!$B$5),0) -> 27 | J15: =ROUNDUP(H15*Assumptions!$B$6,0) -> 4 | K15: =MAX(0,I15+J15-D15) -> 0 | L15: =K15*C15 -> 0 | M15: =IF(H15=0,"No sales",D15/(H15*(1+Assumptions!$B$5))) -> 41.708333 | N15: =IF(AND(D15=0,H15>0),"OUT OF STOCK — reorder now",IF(H15=0,"No sales yet — hold",IF(D15<H15*(1+Assumptions!$B$5)*(Assumptions!$B$7+Assumptions!$B$6),"Reorder soon",IF(K15=0,"Covered for 2027","Reorder in 2027")))) -> Covered for 2027
A16: ADIKT Crew Socks – Yellow | B16: Yellow | C16: ='Current Stock'!F15 -> 10 | D16: ='Current Stock'!G15 -> 90 | E16: 46164 | F16: =MIN(Assumptions!$B$8,MAX(1,ROUND((Assumptions!$B$9-E16)/30.4,1))) -> 4.6 | G16: 9 | H16: =G16/F16 -> 1.9565217 | I16: =ROUNDUP(H16*12*(1+Assumptions!$B$5),0) -> 29 | J16: =ROUNDUP(H16*Assumptions!$B$6,0) -> 4 | K16: =MAX(0,I16+J16-D16) -> 0 | L16: =K16*C16 -> 0 | M16: =IF(H16=0,"No sales",D16/(H16*(1+Assumptions!$B$5))) -> 38.333333 | N16: =IF(AND(D16=0,H16>0),"OUT OF STOCK — reorder now",IF(H16=0,"No sales yet — hold",IF(D16<H16*(1+Assumptions!$B$5)*(Assumptions!$B$7+Assumptions!$B$6),"Reorder soon",IF(K16=0,"Covered for 2027","Reorder in 2027")))) -> Covered for 2027
... A26: ADIKT Red Racing Zip Up | B26: XXL | C26: ='Current Stock'!F25 -> 120 | D26: ='Current Stock'!G25 -> 0 | E26: 45985 | F26: =MIN(Assumptions!$B$8,MAX(1,ROUND((Assumptions!$B$9-E26)/30.4,1))) -> 10.5 | G26: 2 | H26: =G26/F26 -> 0.19047619 | I26: =ROUNDUP(H26*12*(1+Assumptions!$B$5),0) -> 3 | J26: =ROUNDUP(H26*Assumptions!$B$6,0) -> 1 | K26: =MAX(0,I26+J26-D26) -> 4 | L26: =K26*C26 -> 480 | M26: =IF(H26=0,"No sales",D26/(H26*(1+Assumptions!$B$5))) -> 0 | N26: =IF(AND(D26=0,H26>0),"OUT OF STOCK — reorder now",IF(H26=0,"No sales yet — hold",IF(D26<H26*(1+Assumptions!$B$5)*(Assumptions!$B$7+Assumptions!$B$6),"Reorder soon",IF(K26=0,"Covered for 2027","Reorder in 2027")))) -> OUT OF STOCK — reorder now
A27: Total | D27: =SUM(D5:D26) -> 450 | G27: =SUM(G5:G26) -> 44 | I27: =SUM(I5:I26) -> 136 | J27: =SUM(J5:J26) -> 22 | K27: =SUM(K5:K26) -> 28 | L27: =SUM(L5:L26) -> 2905

Sheet Monthly History
A1: Monthly Sales — Oct 2024 to Sep 2026 (all products)
A3: Month | B3: Units sold | C3: Net sales ($)
A4: 2024-10 | B4: 2 | C4: 82
A5: 2024-11 | B5: 16 | C5: 1282.4
A6: 2024-12 | B6: 3 | C6: 209
A7: 2025-01 | B7: 1 | C7: 120
A8: 2025-02 | B8: 0 | C8: 0
A9: 2025-03 | B9: 0 | C9: 0
A10: 2025-04 | B10: 0 | C10: 0
A11: 2025-05 | B11: 0 | C11: 0
A12: 2025-06 | B12: 6 | C12: 215.95
A13: 2025-07 | B13: 11 | C13: 392
A14: 2025-08 | B14: 1 | C14: 36
A15: 2025-09 | B15: 0 | C15: 0
... A27: 2026-09 | B27: 4 | C27: 290
A28: Total | B28: =SUM(B4:B27) -> 158 | C28: =SUM(C4:C27) -> 7693.84
A29: Source: Shopify Analytics, FROM sales SHOW net_items_sold, net_sales TIMESERIES month. October 2026 omitted (month in progress).

Sheet Monthly 2027
A1: 2027 Demand by Month (planned SKUs)
A2: Spreads total 2027 demand from '2027 Plan' using your 24-month seasonality. Use it to time production runs before peaks.
A4: Month | B4: Units sold, last 24 mo | C4: Seasonality share | D4: 2027 demand (units) | E4: Cumulative demand
A5: Jan 2027 | B5: =SUMPRODUCT((RIGHT('Monthly History'!$A$4:$A$27,2)="01")*'Monthly History'!$B$4:$B$27) -> 3 | C5: =IF($B$17=0,1/12,B5/$B$17) -> 0.018987342 | D5: =C5*'2027 Plan'!$I$27 -> 2.5822785 | E5: =SUM($D$5:D5) -> 2.5822785
A6: Feb 2027 | B6: =SUMPRODUCT((RIGHT('Monthly History'!$A$4:$A$27,2)="02")*'Monthly History'!$B$4:$B$27) -> 6 | C6: =IF($B$17=0,1/12,B6/$B$17) -> 0.037974684 | D6: =C6*'2027 Plan'!$I$27 -> 5.164557 | E6: =SUM($D$5:D6) -> 7.7468354
A7: Mar 2027 | B7: =SUMPRODUCT((RIGHT('Monthly History'!$A$4:$A$27,2)="03")*'Monthly History'!$B$4:$B$27) -> 2 | C7: =IF($B$17=0,1/12,B7/$B$17) -> 0.012658228 | D7: =C7*'2027 Plan'!$I$27 -> 1.721519 | E7: =SUM($D$5:D7) -> 9.4683544
A8: Apr 2027 | B8: =SUMPRODUCT((RIGHT('Monthly History'!$A$4:$A$27,2)="04")*'Monthly History'!$B$4:$B$27) -> 0 | C8: =IF($B$17=0,1/12,B8/$B$17) -> 0 | D8: =C8*'2027 Plan'!$I$27 -> 0 | E8: =SUM($D$5:D8) -> 9.4683544
A9: May 2027 | B9: =SUMPRODUCT((RIGHT('Monthly History'!$A$4:$A$27,2)="05")*'Monthly History'!$B$4:$B$27) -> 0 | C9: =IF($B$17=0,1/12,B9/$B$17) -> 0 | D9: =C9*'2027 Plan'!$I$27 -> 0 | E9: =SUM($D$5:D9) -> 9.4683544
A10: Jun 2027 | B10: =SUMPRODUCT((RIGHT('Monthly History'!$A$4:$A$27,2)="06")*'Monthly History'!$B$4:$B$27) -> 6 | C10: =IF($B$17=0,1/12,B10/$B$17) -> 0.037974684 | D10: =C10*'2027 Plan'!$I$27 -> 5.164557 | E10: =SUM($D$5:D10) -> 14.632911
A11: Jul 2027 | B11: =SUMPRODUCT((RIGHT('Monthly History'!$A$4:$A$27,2)="07")*'Monthly History'!$B$4:$B$27) -> 45 | C11: =IF($B$17=0,1/12,B11/$B$17) -> 0.28481013 | D11: =C11*'2027 Plan'!$I$27 -> 38.734177 | E11: =SUM($D$5:D11) -> 53.367089
A12: Aug 2027 | B12: =SUMPRODUCT((RIGHT('Monthly History'!$A$4:$A$27,2)="08")*'Monthly History'!$B$4:$B$27) -> 37 | C12: =IF($B$17=0,1/12,B12/$B$17) -> 0.23417722 | D12: =C12*'2027 Plan'!$I$27 -> 31.848101 | E12: =SUM($D$5:D12) -> 85.21519
A13: Sep 2027 | B13: =SUMPRODUCT((RIGHT('Monthly History'!$A$4:$A$27,2)="09")*'Monthly History'!$B$4:$B$27) -> 4 | C13: =IF($B$17=0,1/12,B13/$B$17) -> 0.025316456 | D13: =C13*'2027 Plan'!$I$27 -> 3.443038 | E13: =SUM($D$5:D13) -> 88.658228
A14: Oct 2027 | B14: =SUMPRODUCT((RIGHT('Monthly History'!$A$4:$A$27,2)="10")*'Monthly History'!$B$4:$B$27) -> 15 | C14: =IF($B$17=0,1/12,B14/$B$17) -> 0.094936709 | D14: =C14*'2027 Plan'!$I$27 -> 12.911392 | E14: =SUM($D$5:D14) -> 101.56962
A15: Nov 2027 | B15: =SUMPRODUCT((RIGHT('Monthly History'!$A$4:$A$27,2)="11")*'Monthly History'!$B$4:$B$27) -> 35 | C15: =IF($B$17=0,1/12,B15/$B$17) -> 0.22151899 | D15: =C15*'2027 Plan'!$I$27 -> 30.126582 | E15: =SUM($D$5:D15) -> 131.6962
A16: Dec 2027 | B16: =SUMPRODUCT((RIGHT('Monthly History'!$A$4:$A$27,2)="12")*'Monthly History'!$B$4:$B$27) -> 5 | C16: =IF($B$17=0,1/12,B16/$B$17) -> 0.03164557 | D16: =C16*'2027 Plan'!$I$27 -> 4.3037975 | E16: =SUM($D$5:D16) -> 136
A17: Total | B17: =SUM(B5:B16) -> 158 | C17: =SUM(C5:C16) -> 1 | D17: =SUM(D5:D16) -> 136
